hatch_ziptz/__init__.py
hatch_ziptz/hooks.py
hatch_ziptz/plugin.py
hatch_ziptz/py.typed
hatch_ziptz/tz.data
hatch_ziptz/tzm.data
hatch_ziptz-2022.11.8.dist-info/METADATA
hatch_ziptz-2022.11.8.dist-info/WHEEL
hatch_ziptz-2022.11.8.dist-info/entry_points.txt
hatch_ziptz-2022.11.8.dist-info/licenses/LICENSE
hatch_ziptz-2022.11.8.dist-info/RECORD
