Metadata-Version: 2.1
Name: hatch-ziptz
Version: 2022.11.8
Summary: Grab the locally-embedded tz database from the ziptz source and plug it into the uploaded project as a json file.
Author-email: "Taylor C. Richberger" <tcr@absolute-performance.com>
Maintainer-email: "Taylor C. Richberger" <tcr@absolute-performance.com>
License: MIT
License-File: LICENSE
Classifier: Development Status :: 5 - Production/Stable
Classifier: Framework :: Hatch
Classifier: License :: OSI Approved :: MIT License
Classifier: Programming Language :: Python :: 3
Requires-Python: >=3.7
Requires-Dist: hatchling
Requires-Dist: importlib-resources<6.0.0,>=5.4.0; python_version < '3.9.0'
